simplerestapi/__init__.py
simplerestapi/api.py
simplerestapi/endpoint.py
simplerestapi/exception.py
simplerestapi/main.py
simplerestapi/model_validator.py
simplerestapi/router.py
simplerestapi/url_params.py
simplerestapi-1.0.2.dist-info/LICENSE
simplerestapi-1.0.2.dist-info/METADATA
simplerestapi-1.0.2.dist-info/WHEEL
simplerestapi-1.0.2.dist-info/top_level.txt
simplerestapi-1.0.2.dist-info/RECORD
