Metadata-Version: 2.1
Name: simplerestapi
Version: 1.0.2
Summary: SimpleRestAPI is the library for launch REST API based on your SQLAlchemy models
Home-page: https://github.com/midezz/simple_api
Author: Andrey Nikulin
Author-email: midezz@gmail.com
License: UNKNOWN
Project-URL: Bug Tracker, https://github.com/midezz/simple_api/issues
Project-URL: Documentation, https://simplerestapi.readthedocs.io/en/latest/
Platform: UNKNOWN
Classifier: Topic :: Internet
Classifier: Topic :: Software Development :: Libraries :: Application Frameworks
Classifier: Topic :: Software Development :: Libraries :: Python Modules
Classifier: Topic :: Software Development :: Libraries
Classifier: Framework :: AsyncIO
Classifier: Programming Language :: Python :: 3.6
Classifier: Programming Language :: Python :: 3.7
Classifier: Programming Language :: Python :: 3.8
Classifier: License :: OSI Approved :: MIT License
Classifier: Topic :: Internet :: WWW/HTTP :: HTTP Servers
Classifier: Topic :: Internet :: WWW/HTTP
Classifier: Operating System :: OS Independent
Requires-Python: >3.6
License-File: LICENSE
Requires-Dist: SQLAlchemy (<=1.3.23,>1.3.0)
Requires-Dist: starlette (<=0.14.2,>0.13.0)
Requires-Dist: pydantic (<=1.8,>1.7)
